{"_id":"61473edb8793aeb7d9315247","chapters":[{"id":460258,"altName":"elena_v1_ch26","chName":"","vol":1,"ch":26,"date":"2019-02-19","dir":"-9new/e/1550528282_elenka26","imagesExt":["png","png","png","png","png","png","png","png","png","png","png","png","png","png","png","png","png","png","png"],"imagesNames":["001","002","003","004","005","006","007","008","009","010","011","012","013","014","015","016","018","019","020"]},{"id":460257,"altName":"elena_v1_ch25","chName":"","vol":1,"ch":25,"date":"2019-02-19","dir":"-9new/e/1550528329_elenka25","imagesExt":["png","png","png","png","png","png","png","png","png","png","png","png","png","png","png","png","png"],"imagesNames":["001","002","003","004","005","006","007","008","009","010","011","012","013","014","015","018","019"]},{"id":455510,"altName":"elena_v1_ch24","chName":"","vol":1,"ch":24,"date":"2019-01-29","dir":"-9new/l/1548758704_lenka24","imagesExt":["png","png","png","png","png","png","png","png","png","png","png","png","png","png"],"imagesNames":["001","002","003","004","005","006","007","008","009","010","011","012","013","014"]},{"id":452044,"altName":"elena_v1_ch23","chName":"","vol":1,"ch":23,"date":"2019-01-13","dir":"-9new/e/1547323256_elena_23","imagesExt":["png","png","png","png","png","png","png","png","png","png","png","png","png","png","png","png"],"imagesNames":["001","002","003","004","005","006","007","008","009","010","011","012","013","014","018","019"]},{"id":449166,"altName":"elena_v1_ch22","chName":"","vol":1,"ch":22,"date":"2018-12-30","dir":"-9new/e/1546114038_elena_22","imagesExt":["png","png","png","png","png","png","png","png","png","png","png","png","png","png","png","png","png","png","png"],"imagesNames":["001","002","003","004","005","006","007","008","009","010","011","012","013","014","015","016","017","018","019"]},{"id":443582,"altName":"elena_v1_ch21","chName":"","vol":1,"ch":21,"date":"2018-11-21","dir":"-9new/2/1542744208_21","imagesExt":["png","png","png","png","png","png","png","png","png","png","png","png","png","png","png","png","png"],"imagesNames":["001","002","003","004","005","006","007","008","009","010","011","012","013","014","015","018","019"]},{"id":437904,"altName":"elena_v1_ch20","chName":"","vol":1,"ch":20,"date":"2018-10-15","dir":"-9new/e/1539546584_elena20","imagesExt":["png","png","png","png","png","png","png","png","png","png","png","png","png","png","png","png","png","png","png"],"imagesNames":["001","002","003","004","005","006","007","008","009","010","011","012","013","014","015","016","017","018","019"]},{"id":436233,"altName":"elena_v1_ch19","chName":"","vol":1,"ch":19,"date":"2018-10-03","dir":"-9new/e/1538514740_elena19","imagesExt":["png","png","png","png","png","png","png","png","png","png","png","png","png","png"],"imagesNames":["001","002","003","004","005","006","007","008","009","010","011","012","016","017"]},{"id":429611,"altName":"elena_v1_ch18","chName":"","vol":1,"ch":18,"date":"2018-08-30","dir":"-9new/1/1535623552_18","imagesExt":["png","png","png","png","png","png","png","png","png","png","png","png","png","png","png","png","png"],"imagesNames":["001","002","003","004","005","006","007","008","009","010","011","012","013","014","015","016","017"]},{"id":429610,"altName":"elena_v1_ch17","chName":"","vol":1,"ch":17,"date":"2018-08-30","dir":"-9new/1/1535623518_17","imagesExt":["png","png","png","png","png","png","png","png","png","png","png","png","png","png"],"imagesNames":["001","002","003","004","005","006","007","008","009","010","011","012","013","014"]},{"id":429609,"altName":"elena_v1_ch16","chName":"","vol":1,"ch":16,"date":"2018-08-30","dir":"-9new/e/1535623579_elena16","imagesExt":["png","png","png","png","png","png","png","png","png","png","png","png","png","png","png","png","png"],"imagesNames":["001","002","003","004","005","006","007","008","009","010","011","012","013","014","015","016","017"]},{"id":423192,"altName":"elena_v1_ch15","chName":"","vol":1,"ch":15,"date":"2018-07-28","dir":"-9new/e/1535623608_elena15-1","imagesExt":["png","png","png","png","png","png","png","png","png","png","png","png","png","png","png"],"imagesNames":["001","002","003","004","005","006","007","008","009","010","011","012","013","014","015"]},{"id":421751,"altName":"elena_v1_ch14","chName":"","vol":1,"ch":14,"date":"2018-07-20","dir":"-9new/e/1532068718_elena14-1","imagesExt":["png","png","png","png","png","png","png","png","png","png","png","png","png","png","png","png"],"imagesNames":["001","002","003","004","005","006","007","008","009","010","011","012","013","014","015","016"]},{"id":419878,"altName":"elena_v1_ch13","chName":"","vol":1,"ch":13,"date":"2018-07-09","dir":"-9new/e/1531075464_elenka_ept_13_taypusik","imagesExt":["png","png","png","png","png","png","png","png","png","png","png","png","png","png","png"],"imagesNames":["001","002","003","004","005","006","007","008","009","010","011","012","013","014","015"]},{"id":418716,"altName":"elena_v1_ch12","chName":"","vol":1,"ch":12,"date":"2018-07-02","dir":"-9new/1/1530476761_12","imagesExt":["png","png","png","png","png","png","png","png","png","png","png","png","png","png","png","png","png","png","png","png","png"],"imagesNames":["001","002","003","004","005","006","007","008","009","010","011","012","013","014","015","016","017","018","019","020","021"]},{"id":410086,"altName":"elena_v1_ch11","chName":"","vol":1,"ch":11,"date":"2018-05-10","dir":"-9new/1/1525877543_11elena","imagesExt":["png","png","png","png","png","png","png","png","png","png","png","png","png","png","png","png","png","png"],"imagesNames":["001","002","003","004","005","006","007","008","009","010","011","012","013","014","015","016","017","018"]},{"id":403684,"altName":"elena_v1_ch10","chName":"","vol":1,"ch":10,"date":"2018-04-09","dir":"-9new/1/1523132951_10","imagesExt":["png","png","png","png","png","png","png","png","png","png","png","png","png","png","png","png","png","png"],"imagesNames":["001","002","003","004","005","006","007","008","009","010","011","012","013","014","015","016","017","018"]},{"id":384961,"altName":"elena_v1_ch9","chName":"","vol":1,"ch":9,"date":"2018-02-02","dir":"-9new/9/1517554262_9","imagesExt":["png","png","png","png","png","png","png","png","png","png","png","png","png","png","png","png","png","png","png","png","png","png"],"imagesNames":["001","002","003","004","005","006","007","008","009","010","011","012","013","014","015","016","017","018","019","020","021","022"]},{"id":377402,"altName":"elena_v1_ch8","chName":"","vol":1,"ch":8,"date":"2018-01-05","dir":"-9new/e/1515143708_elena_v1_ch8","imagesExt":["jpg","jpg","jpg","jpg","jpg","jpg","jpg","jpg","jpg","jpg","jpg","jpg"],"imagesNames":["001._","002._","003._","004._","005._","006._","007._","008._","009._","010._","011._","012._"]},{"id":356688,"altName":"elena_v1_ch7","chName":"","vol":1,"ch":7,"date":"2017-11-27","dir":"-9new/e/1511682770_elena_v1_ch7","imagesExt":["jpg","jpg","jpg","jpg","jpg","jpg","jpg","jpg","jpg","jpg","jpg","jpg","jpg","jpg","jpg","jpg","jpg","jpg"],"imagesNames":["001._","002._","003._","004._","005._","006._","007._","008._","009._","011._","012._","013._","014._","015._","016._","017._","018._","055._"]},{"id":302255,"altName":"elena_v1_ch6","chName":"","vol":1,"ch":6,"date":"2017-02-02","dir":"-9new/e/1486024454_elena_v1_ch6","imagesExt":["jpg","jpg","jpg","jpg","jpg","jpg","jpg","jpg","jpg","jpg","jpg","jpg","jpg","jpg","jpg","jpg","jpg","jpg","jpg"],"imagesNames":["001._","002._","003._","004._","005._","006._","007._","008._","009._","010._","011._","012._","013._","014._","015._","016._","017._","018._","019._"]},{"id":273637,"altName":"elena_v1_ch5","chName":"","vol":1,"ch":5,"date":"2016-07-12","dir":"-9new/e/1468301148_elena_v1_ch5","imagesExt":["jpg","jpg","jpg","jpg","jpg","jpg","jpg","jpg","jpg","jpg","jpg","jpg","jpg","jpg","jpg","jpg","jpg","jpg","jpg"],"imagesNames":["001._","002._","003._","004._","005._","006._","007._","008._","009._","010._","011._","012._","013._","014._","015._","016._","017._","018._","019._"]},{"id":223918,"altName":"elena_v1_ch4","chName":"Ради любви, ради жизни...","vol":1,"ch":4,"date":"2015-07-02","dir":"-9new/e/1435824540_elena_v1_ch4","imagesExt":["jpg","jpg","jpg","jpg","jpg","jpg","jpg","jpg","jpg","jpg","jpg","jpg","jpg","jpg"],"imagesNames":["01","02","03","04._","05","06","07","08","09._","10","11","12._","13._","14"]},{"id":223917,"altName":"elena_v1_ch3","chName":"Удар","vol":1,"ch":3,"date":"2015-07-02","dir":"-9new/e/1435824517_elena_v1_ch3","imagesExt":["jpg","jpg","jpg","jpg","jpg","jpg","jpg","jpg","jpg","jpg","jpg","jpg","jpg","jpg","jpg","jpg","jpg","jpg"],"imagesNames":["001","002._","003","004","005","006","007","008","009","010","011._","012","013","014","015._","016._","017._","018"]},{"id":222899,"altName":"elena_v1_ch2","chName":"Темный брак","vol":1,"ch":2,"date":"2015-06-22","dir":"-9new/e/1434965390_elena_v1_ch2","imagesExt":["jpg","jpg","jpg","jpg","jpg","jpg","jpg","jpg","jpg","jpg","jpg","jpg","jpg","jpg","jpg"],"imagesNames":["e001_143400136591448434","e002_143400136604748434","e003_143400136599948438","e004_143400136597248437","e005_143400136599548433","e006_143400136642048437","e007_143400136658748434","e008_143400136647048438","e009_143400136665848434","e010_143400136667648434","e011_143400136694448432","e012_143400136704748432","e013_143400136728748438","e014_143400136733148431","e015_143400136733148431"]},{"id":222751,"altName":"elena_v1_ch1","chName":"Годовщина","vol":1,"ch":1,"date":"2015-06-21","dir":"-9new/e/1434876644_elena_v1_ch1","imagesExt":["jpg","jpg","jpg","jpg","jpg","jpg","jpg","jpg","jpg","jpg","jpg","jpg","jpg","jpg","jpg","jpg","jpg","jpg"],"imagesNames":["i0019_143351403373348426","i002_143351403373348426","i003_143351403390448428","i004_143351403391748426","i005_143351403390648429","i006_143351403391748427","i007_143351403425948421","i008_143351403465848424","i009_143351403459948420","i010_143351403472748425","i011_143351403481048420","i012_143351403487948428","i013_143351403522948424","i014_143351403541948428","i015_143351403549548425","i016_143351403553248422","i017_143351403555248429","i018_143351403599048423"]}],"constLong":0.34,"countChapters":26,"tags":["ужасы","веб"],"type":"Комикс","shortStory":"Жуткий веб комикс о безумной любви.","translationFull":["Pixel_Horror","City of chains (Город цепей)"],"mangaka":["Jorge Jaramillo"],"transStatus":"Глав: 26, перевод завершен","status":"Томов: 1, выпуск завершен","middleUrl":"manga","img":"/showfull/uploads/posts/2015-11/thumbs/1446443680_i002_143351403373348426.jpg","altName":"elena","rating":16,"title":"Елена (Elena)","apiId":41576,"__v":0}