{"_id":"6147324e8793aeb7d930ff5d","chapters":[{"id":274726,"altName":"kamigami-no-asobi_v3_ch16","chName":"","vol":3,"ch":16,"date":"2016-07-18","dir":"-9new/k/1468823178_kamigami-no-asobi_v3_ch16","imagesExt":["jpg","jpg","jpg","jpg","jpg","jpg","jpg","jpg","jpg","jpg","jpg","jpg","jpg","jpg","jpg","jpg","png","jpg","jpg","jpg","jpg","jpg","jpg","jpg","jpg","jpg","jpg","jpg","jpg","jpg","jpg","jpg","jpg","jpg","jpg","jpg","jpg","jpg","jpg","png"],"imagesNames":["kamigami_no_asobi_v03_ch16_p001._","kamigami_no_asobi_v03_ch16_p002._","kamigami_no_asobi_v03_ch16_p003._","kamigami_no_asobi_v03_ch16_p004._","kamigami_no_asobi_v03_ch16_p005._","kamigami_no_asobi_v03_ch16_p006._","kamigami_no_asobi_v03_ch16_p007._","kamigami_no_asobi_v03_ch16_p008._","kamigami_no_asobi_v03_ch16_p009._","kamigami_no_asobi_v03_ch16_p010._","kamigami_no_asobi_v03_ch16_p011._","kamigami_no_asobi_v03_ch16_p012._","kamigami_no_asobi_v03_ch16_p013._","kamigami_no_asobi_v03_ch16_p014._","kamigami_no_asobi_v03_ch16_p015._","kamigami_no_asobi_v03_ch16_p016._","kamigami_no_asobi_v03_ch16_p017","kamigami_no_asobi_v03_ch16_p018._","kamigami_no_asobi_v03_ch16_p019._","kamigami_no_asobi_v03_ch16_p020._","kamigami_no_asobi_v03_ch16_p021._","kamigami_no_asobi_v03_ch16_p022._","kamigami_no_asobi_v03_ch16_p023._","kamigami_no_asobi_v03_ch16_p024._","kamigami_no_asobi_v03_ch16_p025._","kamigami_no_asobi_v03_ch16_p026._","kamigami_no_asobi_v03_ch16_p027._","kamigami_no_asobi_v03_ch16_p028._","kamigami_no_asobi_v03_ch16_p029._","kamigami_no_asobi_v03_ch16_p030._","kamigami_no_asobi_v03_ch16_p031._","kamigami_no_asobi_v03_ch16_p032._","kamigami_no_asobi_v03_ch16_p033._","kamigami_no_asobi_v03_ch16_p034._","kamigami_no_asobi_v03_ch16_p035._","kamigami_no_asobi_v03_ch16_p036._","kamigami_no_asobi_v03_ch16_p037._","kamigami_no_asobi_v03_ch16_p038._","kamigami_no_asobi_v03_ch16_p039._","kamigami_no_asobi_v03_ch16_p040"]},{"id":274725,"altName":"kamigami-no-asobi_v3_ch15","chName":"","vol":3,"ch":15,"date":"2016-07-18","dir":"-9new/k/1468823206_kamigami-no-asobi_v3_ch15","imagesExt":["jpg","jpg","jpg","jpg","jpg","jpg","jpg","jpg","jpg","jpg","jpg","jpg","jpg","jpg","jpg","jpg","jpg","jpg","jpg","jpg","jpg","jpg","jpg","jpg","jpg","jpg","jpg","jpg","jpg","png"],"imagesNames":["kamigami_no_asobi_v03_ch15_p001._","kamigami_no_asobi_v03_ch15_p002._","kamigami_no_asobi_v03_ch15_p003._","kamigami_no_asobi_v03_ch15_p004._","kamigami_no_asobi_v03_ch15_p005._","kamigami_no_asobi_v03_ch15_p006._","kamigami_no_asobi_v03_ch15_p007._","kamigami_no_asobi_v03_ch15_p008._","kamigami_no_asobi_v03_ch15_p009._","kamigami_no_asobi_v03_ch15_p010._","kamigami_no_asobi_v03_ch15_p011._","kamigami_no_asobi_v03_ch15_p012._","kamigami_no_asobi_v03_ch15_p013._","kamigami_no_asobi_v03_ch15_p014._","kamigami_no_asobi_v03_ch15_p015._","kamigami_no_asobi_v03_ch15_p016._","kamigami_no_asobi_v03_ch15_p017._","kamigami_no_asobi_v03_ch15_p018._","kamigami_no_asobi_v03_ch15_p019._","kamigami_no_asobi_v03_ch15_p020._","kamigami_no_asobi_v03_ch15_p021._","kamigami_no_asobi_v03_ch15_p022._","kamigami_no_asobi_v03_ch15_p023._","kamigami_no_asobi_v03_ch15_p024._","kamigami_no_asobi_v03_ch15_p025._","kamigami_no_asobi_v03_ch15_p026._","kamigami_no_asobi_v03_ch15_p027._","kamigami_no_asobi_v03_ch15_p028._","kamigami_no_asobi_v03_ch15_p029._","kamigami_no_asobi_v03_ch15_p030"]},{"id":274724,"altName":"kamigami-no-asobi_v3_ch14","chName":"","vol":3,"ch":14,"date":"2016-07-18","dir":"-9new/k/1468823174_kamigami-no-asobi_v3_ch14","imagesExt":["jpg","jpg","png","png","jpg","jpg","jpg","jpg","jpg","jpg","jpg","jpg","jpg","jpg","jpg","jpg","png","jpg","jpg","jpg","jpg","jpg","jpg","jpg","jpg","jpg","jpg","jpg","jpg","png"],"imagesNames":["kamigami_no_asobi_v03_ch14_p001._","kamigami_no_asobi_v03_ch14_p002._","kamigami_no_asobi_v03_ch14_p003","kamigami_no_asobi_v03_ch14_p004","kamigami_no_asobi_v03_ch14_p005._","kamigami_no_asobi_v03_ch14_p006._","kamigami_no_asobi_v03_ch14_p007._","kamigami_no_asobi_v03_ch14_p008._","kamigami_no_asobi_v03_ch14_p009._","kamigami_no_asobi_v03_ch14_p010._","kamigami_no_asobi_v03_ch14_p011._","kamigami_no_asobi_v03_ch14_p012._","kamigami_no_asobi_v03_ch14_p013._","kamigami_no_asobi_v03_ch14_p014._","kamigami_no_asobi_v03_ch14_p015._","kamigami_no_asobi_v03_ch14_p016._","kamigami_no_asobi_v03_ch14_p017","kamigami_no_asobi_v03_ch14_p018._","kamigami_no_asobi_v03_ch14_p019._","kamigami_no_asobi_v03_ch14_p020._","kamigami_no_asobi_v03_ch14_p021._","kamigami_no_asobi_v03_ch14_p022._","kamigami_no_asobi_v03_ch14_p023._","kamigami_no_asobi_v03_ch14_p024._","kamigami_no_asobi_v03_ch14_p025._","kamigami_no_asobi_v03_ch14_p026._","kamigami_no_asobi_v03_ch14_p027._","kamigami_no_asobi_v03_ch14_p028._","kamigami_no_asobi_v03_ch14_p029._","kamigami_no_asobi_v03_ch14_p030"]},{"id":269033,"altName":"kamigami-no-asobi_v3_ch13","chName":"","vol":3,"ch":13,"date":"2016-06-10","dir":"-9new/k/1465541386_kamigami-no-asobi_v3_ch13","imagesExt":["jpg","jpg","jpg","jpg","jpg","jpg","jpg","jpg","jpg","jpg","jpg","jpg","jpg","jpg","jpg","jpg","jpg","jpg","jpg","jpg","jpg","jpg","jpg","jpg","jpg","jpg","jpg","png","jpg"],"imagesNames":["kamigami_no_asobi_v03_ch13_p001._","kamigami_no_asobi_v03_ch13_p002._","kamigami_no_asobi_v03_ch13_p003._","kamigami_no_asobi_v03_ch13_p004._","kamigami_no_asobi_v03_ch13_p005._","kamigami_no_asobi_v03_ch13_p006._","kamigami_no_asobi_v03_ch13_p007._","kamigami_no_asobi_v03_ch13_p008._","kamigami_no_asobi_v03_ch13_p009._","kamigami_no_asobi_v03_ch13_p010._","kamigami_no_asobi_v03_ch13_p011._","kamigami_no_asobi_v03_ch13_p012._","kamigami_no_asobi_v03_ch13_p013._","kamigami_no_asobi_v03_ch13_p014._","kamigami_no_asobi_v03_ch13_p015._","kamigami_no_asobi_v03_ch13_p016._","kamigami_no_asobi_v03_ch13_p017._","kamigami_no_asobi_v03_ch13_p018._","kamigami_no_asobi_v03_ch13_p019._","kamigami_no_asobi_v03_ch13_p020._","kamigami_no_asobi_v03_ch13_p021._","kamigami_no_asobi_v03_ch13_p022._","kamigami_no_asobi_v03_ch13_p023._","kamigami_no_asobi_v03_ch13_p024._","kamigami_no_asobi_v03_ch13_p025._","kamigami_no_asobi_v03_ch13_p026._","kamigami_no_asobi_v03_ch13_p027._","kamigami_no_asobi_v03_ch13_p028","kamigami_no_asobi_v03_ch13_p029._"]},{"id":267716,"altName":"kamigami-no-asobi_v3_ch12","chName":"","vol":3,"ch":12,"date":"2016-05-31","dir":"-9new/k/1464711700_kamigami-no-asobi_v3_ch12","imagesExt":["jpg","jpg","jpg","jpg","jpg","jpg","jpg","jpg","jpg","jpg","jpg","jpg","jpg","jpg","jpg","jpg","jpg","jpg","jpg","jpg","jpg","jpg","jpg","jpg","jpg","jpg","jpg","png","png"],"imagesNames":["kamigami_no_asobi_v03_ch12_p001._","kamigami_no_asobi_v03_ch12_p002._","kamigami_no_asobi_v03_ch12_p003._","kamigami_no_asobi_v03_ch12_p004._","kamigami_no_asobi_v03_ch12_p005._","kamigami_no_asobi_v03_ch12_p006._","kamigami_no_asobi_v03_ch12_p007._","kamigami_no_asobi_v03_ch12_p008._","kamigami_no_asobi_v03_ch12_p009._","kamigami_no_asobi_v03_ch12_p010._","kamigami_no_asobi_v03_ch12_p011._","kamigami_no_asobi_v03_ch12_p012._","kamigami_no_asobi_v03_ch12_p013._","kamigami_no_asobi_v03_ch12_p014._","kamigami_no_asobi_v03_ch12_p015._","kamigami_no_asobi_v03_ch12_p016._","kamigami_no_asobi_v03_ch12_p017._","kamigami_no_asobi_v03_ch12_p018._","kamigami_no_asobi_v03_ch12_p019._","kamigami_no_asobi_v03_ch12_p020._","kamigami_no_asobi_v03_ch12_p021._","kamigami_no_asobi_v03_ch12_p022._","kamigami_no_asobi_v03_ch12_p023._","kamigami_no_asobi_v03_ch12_p024._","kamigami_no_asobi_v03_ch12_p025._","kamigami_no_asobi_v03_ch12_p026._","kamigami_no_asobi_v03_ch12_p027._","kamigami_no_asobi_v03_ch12_p028","kamigami_no_asobi_v03_ch12_p029"]},{"id":264523,"altName":"kamigami-no-asobi_v2_ch11","chName":"","vol":2,"ch":11,"date":"2016-05-03","dir":"-9new/k/1462254281_kamigami-no-asobi_v2_ch11","imagesExt":["jpg","png","png","png","jpg","jpg","jpg","jpg","jpg","jpg","jpg","jpg","jpg","jpg","jpg","jpg","jpg","jpg","jpg","jpg","jpg","jpg","jpg","jpg","jpg","jpg","jpg","jpg","png"],"imagesNames":["kamigami_no_asobi_v02_ch11_p001._","kamigami_no_asobi_v02_ch11_p002","kamigami_no_asobi_v02_ch11_p003","kamigami_no_asobi_v02_ch11_p004","kamigami_no_asobi_v02_ch11_p005._","kamigami_no_asobi_v02_ch11_p006._","kamigami_no_asobi_v02_ch11_p007._","kamigami_no_asobi_v02_ch11_p008._","kamigami_no_asobi_v02_ch11_p009._","kamigami_no_asobi_v02_ch11_p010._","kamigami_no_asobi_v02_ch11_p011._","kamigami_no_asobi_v02_ch11_p012._","kamigami_no_asobi_v02_ch11_p013._","kamigami_no_asobi_v02_ch11_p014._","kamigami_no_asobi_v02_ch11_p015._","kamigami_no_asobi_v02_ch11_p016._","kamigami_no_asobi_v02_ch11_p017._","kamigami_no_asobi_v02_ch11_p018._","kamigami_no_asobi_v02_ch11_p019._","kamigami_no_asobi_v02_ch11_p020._","kamigami_no_asobi_v02_ch11_p021._","kamigami_no_asobi_v02_ch11_p022._","kamigami_no_asobi_v02_ch11_p023._","kamigami_no_asobi_v02_ch11_p024._","kamigami_no_asobi_v02_ch11_p025._","kamigami_no_asobi_v02_ch11_p026._","kamigami_no_asobi_v02_ch11_p027._","kamigami_no_asobi_v02_ch11_p028._","kamigami_no_asobi_v02_ch11_p029"]},{"id":261053,"altName":"kamigami-no-asobi_v2_ch10","chName":"","vol":2,"ch":10,"date":"2016-04-06","dir":"-9new/k/1459928286_kamigami-no-asobi_v2_ch10","imagesExt":["jpg","png","png","png","png","png","png","jpg","png","png","png","png","png","png","png","png","png","png","png","png","png","png","png","png","png","png","png"],"imagesNames":["zz_0001_6751._","zz_0002_5367","zz_0003_2647","zz_0004_2982","zz_0005_0270","zz_0006_4259","zz_0007_5070","zz_0008_1269._","zz_0009_5891","zz_0010_5118","zz_0011_6267","zz_0012_5255","zz_0013_9756","zz_0014_7087","zz_0015_5651","zz_0016_4730","zz_0017_3892","zz_0018_9343","zz_0019_0448","zz_0020_2742","zz_0021_5208","zz_0022_3950","zz_0023_2435","zz_0024_0366","zz_0025_9912","zz_0026_4214","zz_0027_4214"]},{"id":256249,"altName":"kamigami-no-asobi_v2_ch9","chName":"","vol":2,"ch":9,"date":"2016-03-01","dir":"-9new/k/1456807115_kamigami-no-asobi_v2_ch9","imagesExt":["png","jpg","png","png","jpg","png","png","png","png","png","jpg","png","png","png","png","png","png","png","png","jpg","png","png","png","png","png","png","png"],"imagesNames":["kamigami_no_asobi_v02_ch09_p001","kamigami_no_asobi_v02_ch09_p002._","kamigami_no_asobi_v02_ch09_p003","kamigami_no_asobi_v02_ch09_p004","kamigami_no_asobi_v02_ch09_p005._","kamigami_no_asobi_v02_ch09_p006","kamigami_no_asobi_v02_ch09_p007","kamigami_no_asobi_v02_ch09_p008","kamigami_no_asobi_v02_ch09_p009","kamigami_no_asobi_v02_ch09_p010","kamigami_no_asobi_v02_ch09_p011._","kamigami_no_asobi_v02_ch09_p012","kamigami_no_asobi_v02_ch09_p013","kamigami_no_asobi_v02_ch09_p014","kamigami_no_asobi_v02_ch09_p015","kamigami_no_asobi_v02_ch09_p016","kamigami_no_asobi_v02_ch09_p017","kamigami_no_asobi_v02_ch09_p018","kamigami_no_asobi_v02_ch09_p019","kamigami_no_asobi_v02_ch09_p020._","kamigami_no_asobi_v02_ch09_p021","kamigami_no_asobi_v02_ch09_p022","kamigami_no_asobi_v02_ch09_p023","kamigami_no_asobi_v02_ch09_p024","kamigami_no_asobi_v02_ch09_p025","kamigami_no_asobi_v02_ch09_p026","kamigami_no_asobi_v02_ch09_p027"]},{"id":246260,"altName":"kamigami-no-akugi_v2_ch8","chName":"","vol":2,"ch":8,"date":"2016-01-01","dir":"-9new/k/1451635044_kamigami-no-asobi_v2_ch7","imagesExt":["jpg","jpg","jpg","jpg","png","jpg","jpg","jpg","jpg","jpg","jpg","jpg","jpg","jpg","jpg","jpg","jpg","jpg","jpg","jpg","jpg","jpg","jpg","jpg","jpg","png","jpg"],"imagesNames":["kamigami_no_asobi_v02_ch08_p001.png._","kamigami_no_asobi_v02_ch08_p002.png._","kamigami_no_asobi_v02_ch08_p003.png._","kamigami_no_asobi_v02_ch08_p004.png._","kamigami_no_asobi_v02_ch08_p005.png","kamigami_no_asobi_v02_ch08_p006.png._","kamigami_no_asobi_v02_ch08_p007.png._","kamigami_no_asobi_v02_ch08_p008.png._","kamigami_no_asobi_v02_ch08_p009.png._","kamigami_no_asobi_v02_ch08_p010.png._","kamigami_no_asobi_v02_ch08_p011.png._","kamigami_no_asobi_v02_ch08_p012.png._","kamigami_no_asobi_v02_ch08_p013.png._","kamigami_no_asobi_v02_ch08_p014png._","kamigami_no_asobi_v02_ch08_p015.png._","kamigami_no_asobi_v02_ch08_p016.png._","kamigami_no_asobi_v02_ch08_p017.png._","kamigami_no_asobi_v02_ch08_p018.png._","kamigami_no_asobi_v02_ch08_p019.png._","kamigami_no_asobi_v02_ch08_p020.png._","kamigami_no_asobi_v02_ch08_p021.png._","kamigami_no_asobi_v02_ch08_p022.png._","kamigami_no_asobi_v02_ch08_p023.png._","kamigami_no_asobi_v02_ch08_p024.png._","kamigami_no_asobi_v02_ch08_p025.png._","kamigami_no_asobi_v02_ch08_p026.png","kamigami_no_asobi_v02_ch08_p027.png._"]},{"id":246259,"altName":"kamigami-no-akugi_v2_ch7","chName":"","vol":2,"ch":7,"date":"2016-01-01","dir":"-9new/k/1451634992_kamigami-no-asobi_v1_ch7","imagesExt":["jpg","jpg","jpg","jpg","jpg","jpg","jpg","jpg","jpg","jpg","jpg","jpg","jpg","jpg","jpg","jpg","png","jpg"],"imagesNames":["kamigami_no_asobi_v02_ch07_p001.png._","kamigami_no_asobi_v02_ch07_p002.png._","kamigami_no_asobi_v02_ch07_p003.png._","kamigami_no_asobi_v02_ch07_p004.png._","kamigami_no_asobi_v02_ch07_p005.png._","kamigami_no_asobi_v02_ch07_p006.png._","kamigami_no_asobi_v02_ch07_p007.png._","kamigami_no_asobi_v02_ch07_p008.png._","kamigami_no_asobi_v02_ch07_p009.png._","kamigami_no_asobi_v02_ch07_p010.png._","kamigami_no_asobi_v02_ch07_p011.png._","kamigami_no_asobi_v02_ch07_p012.png._","kamigami_no_asobi_v02_ch07_p013.png._","kamigami_no_asobi_v02_ch07_p014.png._","kamigami_no_asobi_v02_ch07_p015.png._","kamigami_no_asobi_v02_ch07_p016.png._","kamigami_no_asobi_v02_ch07_p017.png","kamigami_no_asobi_v02_ch07_p018.png._"]},{"id":244913,"altName":"kamigami-no-asobi_v1_ch6","chName":"","vol":1,"ch":6,"date":"2015-12-21","dir":"-9new/k/1450689439_kamigami-no-asobi_v1_ch6","imagesExt":["jpg","jpg","png","jpg","jpg","jpg","jpg","jpg","jpg","jpg","jpg","jpg","jpg","jpg","jpg","jpg","jpg","jpg","jpg","jpg","jpg","jpg","png"],"imagesNames":["kamigami_no_asobi_v01_ch06_p001.png._","kamigami_no_asobi_v01_ch06_p002.png._","kamigami_no_asobi_v01_ch06_p003.png","kamigami_no_asobi_v01_ch06_p004.png._","kamigami_no_asobi_v01_ch06_p005.png._","kamigami_no_asobi_v01_ch06_p006.png._","kamigami_no_asobi_v01_ch06_p007.png._","kamigami_no_asobi_v01_ch06_p008.png._","kamigami_no_asobi_v01_ch06_p009.png._","kamigami_no_asobi_v01_ch06_p010.png._","kamigami_no_asobi_v01_ch06_p011.png._","kamigami_no_asobi_v01_ch06_p012.png._","kamigami_no_asobi_v01_ch06_p013.png._","kamigami_no_asobi_v01_ch06_p014.png._","kamigami_no_asobi_v01_ch06_p015.png._","kamigami_no_asobi_v01_ch06_p016.png._","kamigami_no_asobi_v01_ch06_p017.png._","kamigami_no_asobi_v01_ch06_p018.png._","kamigami_no_asobi_v01_ch06_p019.png._","kamigami_no_asobi_v01_ch06_p020.png._","kamigami_no_asobi_v01_ch06_p021.png._","kamigami_no_asobi_v01_ch06_p022.png._","kamigami_no_asobi_v01_ch06_p023.png"]},{"id":239966,"altName":"kamigami-no-asobi_v1_ch5","chName":"","vol":1,"ch":5,"date":"2015-11-09","dir":"-9new/k/1447000556_kamigami-no-asobi_v1_ch5","imagesExt":["png","png","png","png","png","png","png","png","png","png","png","png","png","png","png","png","png","png","png"],"imagesNames":["kamigami_no_asobi_ch_05_002","kamigami_no_asobi_ch_05_003","kamigami_no_asobi_ch_05_004","kamigami_no_asobi_ch_05_005","kamigami_no_asobi_ch_05_006","kamigami_no_asobi_ch_05_007","kamigami_no_asobi_ch_05_008","kamigami_no_asobi_ch_05_009","kamigami_no_asobi_ch_05_010","kamigami_no_asobi_ch_05_011","kamigami_no_asobi_ch_05_012","kamigami_no_asobi_ch_05_013","kamigami_no_asobi_ch_05_014","kamigami_no_asobi_ch_05_015","kamigami_no_asobi_ch_05_016","kamigami_no_asobi_ch_05_017","kamigami_no_asobi_ch_05_018","kamigami_no_asobi_ch_05_019","kamigami_no_asobi_ch_05_020"]},{"id":221842,"altName":"kamigami-no-asobi_v1_ch4","chName":"","vol":1,"ch":4,"date":"2015-06-11","dir":"-9new/k/1434008532_kamigami-no-asobi_v1_ch4","imagesExt":["jpg","jpg","jpg","jpg","jpg","jpg","jpg","jpg","jpg","jpg","jpg","jpg","jpg","jpg","jpg","jpg","jpg","jpg","jpg","jpg","jpg"],"imagesNames":["shufflyparfait_kna_ch004_pg001","shufflyparfait_kna_ch004_pg002","shufflyparfait_kna_ch004_pg003","shufflyparfait_kna_ch004_pg004","shufflyparfait_kna_ch004_pg005","shufflyparfait_kna_ch004_pg006","shufflyparfait_kna_ch004_pg007","shufflyparfait_kna_ch004_pg008","shufflyparfait_kna_ch004_pg009","shufflyparfait_kna_ch004_pg010","shufflyparfait_kna_ch004_pg011","shufflyparfait_kna_ch004_pg012","shufflyparfait_kna_ch004_pg013","shufflyparfait_kna_ch004_pg014","shufflyparfait_kna_ch004_pg015","shufflyparfait_kna_ch004_pg016","shufflyparfait_kna_ch004_pg017","shufflyparfait_kna_ch004_pg018","shufflyparfait_kna_ch004_pg019","shufflyparfait_kna_ch004_pg020","shufflyparfait_kna_ch004_pg021"]},{"id":193146,"altName":"kamigami-no-akugi_v1_ch3","chName":"","vol":1,"ch":3,"date":"2014-08-23","dir":"-9new/k/1408777119_kamigami_no_asobi_v01_ch03","imagesExt":["png","png","png","png","png","png","png","png","png","png","png","png","png","png","png","png","png","png"],"imagesNames":["kamigami_no_asobi_v01_ch03_p001","kamigami_no_asobi_v01_ch03_p002","kamigami_no_asobi_v01_ch03_p003","kamigami_no_asobi_v01_ch03_p004","kamigami_no_asobi_v01_ch03_p005","kamigami_no_asobi_v01_ch03_p006","kamigami_no_asobi_v01_ch03_p007","kamigami_no_asobi_v01_ch03_p008","kamigami_no_asobi_v01_ch03_p009","kamigami_no_asobi_v01_ch03_p010","kamigami_no_asobi_v01_ch03_p011","kamigami_no_asobi_v01_ch03_p012","kamigami_no_asobi_v01_ch03_p013","kamigami_no_asobi_v01_ch03_p014","kamigami_no_asobi_v01_ch03_p015","kamigami_no_asobi_v01_ch03_p016","kamigami_no_asobi_v01_ch03_p017","wanted"]},{"id":185784,"altName":"kamigami-no-akugi_v1_ch2","chName":"","vol":1,"ch":2,"date":"2014-06-07","dir":"-9new/k/1402154281_kamigami_no_asobi_v01_ch02","imagesExt":["png","png","png","png","png","png","png","png","png","png","png","png","png","png","png","png","png"],"imagesNames":["kamigami_no_asobi_v01_ch02_p001","kamigami_no_asobi_v01_ch02_p002","kamigami_no_asobi_v01_ch02_p003","kamigami_no_asobi_v01_ch02_p004","kamigami_no_asobi_v01_ch02_p005","kamigami_no_asobi_v01_ch02_p006","kamigami_no_asobi_v01_ch02_p007","kamigami_no_asobi_v01_ch02_p008","kamigami_no_asobi_v01_ch02_p009","kamigami_no_asobi_v01_ch02_p010","kamigami_no_asobi_v01_ch02_p011","kamigami_no_asobi_v01_ch02_p012","kamigami_no_asobi_v01_ch02_p013","kamigami_no_asobi_v01_ch02_p014","kamigami_no_asobi_v01_ch02_p015","kamigami_no_asobi_v01_ch02_p016","kamigami_no_asobi_v01_ch02_p017"]},{"id":184673,"altName":"kamigami-no-akugi_v1_ch1","chName":"","vol":1,"ch":1,"date":"2014-05-24","dir":"-9new/k/1400939270_kamigami_no_asobi_v01_ch01","imagesExt":["png","png","png","png","png","png","png","png","png","png","png","png","png","png","png","png","png","png","png","png","png","png","png","png","png","png","png","png","png","png","png","png","png","png","png","png","png","png","png","png","png","png","png"],"imagesNames":["kamigami_no_asobi_v01_ch01_p001","kamigami_no_asobi_v01_ch01_p002","kamigami_no_asobi_v01_ch01_p003","kamigami_no_asobi_v01_ch01_p004","kamigami_no_asobi_v01_ch01_p005","kamigami_no_asobi_v01_ch01_p006","kamigami_no_asobi_v01_ch01_p007","kamigami_no_asobi_v01_ch01_p008","kamigami_no_asobi_v01_ch01_p009","kamigami_no_asobi_v01_ch01_p010","kamigami_no_asobi_v01_ch01_p011","kamigami_no_asobi_v01_ch01_p012","kamigami_no_asobi_v01_ch01_p013","kamigami_no_asobi_v01_ch01_p014","kamigami_no_asobi_v01_ch01_p015","kamigami_no_asobi_v01_ch01_p016","kamigami_no_asobi_v01_ch01_p017","kamigami_no_asobi_v01_ch01_p018","kamigami_no_asobi_v01_ch01_p019","kamigami_no_asobi_v01_ch01_p020","kamigami_no_asobi_v01_ch01_p021","kamigami_no_asobi_v01_ch01_p022","kamigami_no_asobi_v01_ch01_p023","kamigami_no_asobi_v01_ch01_p024-025","kamigami_no_asobi_v01_ch01_p026","kamigami_no_asobi_v01_ch01_p027","kamigami_no_asobi_v01_ch01_p028","kamigami_no_asobi_v01_ch01_p029","kamigami_no_asobi_v01_ch01_p030","kamigami_no_asobi_v01_ch01_p031","kamigami_no_asobi_v01_ch01_p032","kamigami_no_asobi_v01_ch01_p033","kamigami_no_asobi_v01_ch01_p034","kamigami_no_asobi_v01_ch01_p035","kamigami_no_asobi_v01_ch01_p036","kamigami_no_asobi_v01_ch01_p037","kamigami_no_asobi_v01_ch01_p038","kamigami_no_asobi_v01_ch01_p039","kamigami_no_asobi_v01_ch01_p040","kamigami_no_asobi_v01_ch01_p041","kamigami_no_asobi_v01_ch01_p042","kamigami_no_asobi_v01_ch01_p043","kamigami_no_asobi_v01_ch01_p044"]}],"constLong":0.34,"countChapters":16,"tags":["гарем","романтика","сёдзё","школа","сверхъестественное"],"type":"Манга","shortStory":"Это история о мире, в котором собраны различные Боги из разных мифологий. Типичные представители Богов собрались на совет. На повестке дня - Боги с трудным характером, которые возненавидели людей. Но Боги должны любить людей, а те им поклоняться. Печально, но если так пойдет и дальше, связь между Богами и людьми будет разорвана. Было решено нарушить статус-кво и создать подобие человеческого учебного заведения «школа», выбрать одну человеческую девушку и приказать ей научить проблемных Богов, что такое человек и что такое любовь. Таким образом, наша главная героиня, Кусанаги Юи, отправляется жить и учиться в школе с Богами…","translationFull":["Neko Scans","Crystal Storm"],"mangaka":["Broccoli","SUMIDA Moto"],"transStatus":"Глав: 16, перевод завершен","status":"Томов: 3, выпуск завершен","middleUrl":"manga","img":"/showfull/uploads/posts/2014-05/thumbs/1400947532_1400832773_67106208.jpg","altName":"kamigami-no-akugi","rating":130,"title":"Забавы богов (Kamigami no Akugi)","apiId":31638,"__v":0}