{"_id":"6147434f8793aeb7d9317193","chapters":[{"id":333138,"altName":"the-black-brick-road-of-oz_v1_ch1","chName":"","vol":1,"ch":1,"date":"2017-08-20","dir":"-9new/t/1503149713_the-black-brick-road-of-oz_v1_ch1","imagesExt":["jpg","jpg","jpg","jpg","jpg","jpg","jpg","jpg","jpg","jpg","jpg","jpg"],"imagesNames":["____________-0._","____________-1.5._","____________-1._","______._1._","______._2._","______._3._","______._4._","______._5._","______._6._","______._7._","______._8._","______._9._"]}],"constLong":0.34,"countChapters":1,"tags":["сверхъестественное","приключения"],"type":"Комикс","shortStory":"","translationFull":["Швеция одобряет","ПеченькО с ВареньеМ"],"mangaka":["Xamag"],"transStatus":"Глав: 1, перевод продолжается","status":"Томов: 1, выпуск завершен","middleUrl":"manga","img":"/showfull/uploads/posts/2017-08/thumbs/1503206368_____________-1.5._.jpg","altName":"the-black-brick-road-of-oz","rating":6,"title":"Черная кирпичная дорога в Оз (The black brick road of oz)","apiId":74779,"__v":0}